phreeqcrm/__init__.py
phreeqcrm/_phreeqcrm.cpython-312-i386-linux-musl.so
phreeqcrm/phreeqcrm.py
phreeqcrm/yamlphreeqcrm.py
phreeqcrm.libs/libgcc_s-e1925712.so.1
phreeqcrm.libs/libgomp-6d7f45f1.so.1.0.0
phreeqcrm.libs/libstdc++-b2d5af4b.so.6.0.33
phreeqcrm-0.0.17.dist-info/METADATA
phreeqcrm-0.0.17.dist-info/WHEEL
phreeqcrm-0.0.17.dist-info/RECORD
phreeqcrm-0.0.17.dist-info/licenses/LICENSE
