Metadata-Version: 2.2
Name: phreeqcrm
Version: 0.0.17
Summary: A reaction module for transport simulators based on the geochemical model PHREEQC.
Classifier: Development Status :: 4 - Beta
Classifier: License :: CC0 1.0 Universal (CC0 1.0) Public Domain Dedication
Classifier: Programming Language :: Python :: 3 :: Only
Classifier: Programming Language :: Python :: 3.11
Classifier: Programming Language :: Python :: 3.12
Classifier: Programming Language :: Python :: 3.13
Classifier: Programming Language :: Python :: 3.14
Requires-Python: >=3.11
Requires-Dist: numpy
Requires-Dist: PyYAML
